{
    "configurations": [
        {
            "name": "Win32",
            "includePath": [
                "C:\\Users\\ren66\\AppData\\Local\\Arduino15\\packages\\arduino\\tools\\**",
                "C:\\Users\\ren66\\OneDrive\\Documents\\Arduino\\libraries\\**",
                "E:\\Program Files (x86)\\Arduino\\libraries\\**",
                "C:\\Users\\ren66\\AppData\\Local\\Arduino15\\packages\\arduino\\hardware\\samd\\1.8.11\\**"
            ],
            "forcedInclude": [
                "C:\\Users\\ren66\\AppData\\Local\\Arduino15\\packages\\arduino\\hardware\\samd\\1.8.11\\cores\\arduino\\Arduino.h"
            ],
            "defines": [
                "USBCON"
            ],
            "intelliSenseMode": "windows-msvc-x64",
            "compilerPath": "C:/Program Files (x86)/Microsoft Visual Studio/2019/Community/VC/Tools/MSVC/14.28.29333/bin/Hostx64/x64/cl.exe",
            "cStandard": "c17",
            "cppStandard": "c++17"
        }
    ],
    "version": 4
}